lusid_yevbarkalov/__init__.py
lusid_yevbarkalov/lusid.py
lusid_yevbarkalov-0.0.1.dist-info/LICENSE
lusid_yevbarkalov-0.0.1.dist-info/METADATA
lusid_yevbarkalov-0.0.1.dist-info/WHEEL
lusid_yevbarkalov-0.0.1.dist-info/top_level.txt
lusid_yevbarkalov-0.0.1.dist-info/RECORD
