Metadata-Version: 2.1
Name: lusid_yevbarkalov
Version: 0.0.1
Summary: Manage iMessage with python
Author-email: Yev Barkalov <yev@lsd.so>
Project-URL: Homepage, https://github.com/yevbar/lusid
Project-URL: Issues, https://github.com/yevbar/lusid/issues
Classifier: Programming Language :: Python :: 3
Classifier: License :: OSI Approved :: MIT License
Classifier: Operating System :: MacOS
Requires-Python: >=3.8
License-File: LICENSE
